{"analysisResults":[{"rmsDistanceRatio":0.046432977747601946},{"rmsDistanceRatio":0.009408086443917427},{"rmsDistanceRatio":0.005346181912638256},{"rmsDistanceRatio":0.04197187601957636}],"scenario":{"lighting":"../../../shared-assets/environments/lightroom_14b.hdr","dimensions":{"width":768,"height":600},"target":{"x":-0.18,"y":0,"z":0},"orbit":{"theta":0,"phi":90,"radius":1.1},"verticalFoV":45,"renderSkybox":false,"name":"khronos-SpecularTest","model":"../../../shared-assets/models/glTF-Sample-Models/2.0/SpecularTest/glTF-Binary/SpecularTest.glb","exclude":["stellar"]}}